votifier2/__init__.py
votifier2/exceptions.py
votifier2/server.py
votifier2/vote.py
votifier2-0.1.0.dist-info/LICENSE.md
votifier2-0.1.0.dist-info/METADATA
votifier2-0.1.0.dist-info/WHEEL
votifier2-0.1.0.dist-info/top_level.txt
votifier2-0.1.0.dist-info/RECORD
